{"_id":{"$oid":"6339d5f923a9f0b02e6b5a41"},"UserID":"hb","Response":[{"questionNumber":0,"input1":8,"input2":5,"input3":9,"input4":6,"input5":0,"input6":0,"input7":0,"input8":0,"_id":{"$oid":"6339d60623a9f0b02e6b5a44"}},{"questionNumber":1,"input1":9,"input2":8,"input3":9,"input4":7,"input5":null,"input6":null,"input7":null,"input8":null,"_id":{"$oid":"6339d60c23a9f0b02e6b5a49"}}],"__v":0}
{"_id":{"$oid":"6339d65328032a3813f0b92f"},"UserID":"hb-1","Response":[],"__v":0}
{"_id":{"$oid":"6339debde92abc23ec237dc6"},"UserID":"jasmine","Response":[],"__v":0}
{"_id":{"$oid":"6339e22859d711dd8577d2bd"},"UserID":"hb-2","Response":[],"__v":0}
{"_id":{"$oid":"6339e29426cac0a05a01549e"},"UserID":"hb-9","Response":[],"__v":0}
{"_id":{"$oid":"6339e399a1fe98b560f03a9f"},"UserID":"hb-8","Response":[],"__v":0}
